{
  "sheet": "D:\\projects\\practice\\haka_comic\\assets\\icons\\concepts\\haka-combo-clever-preview.png",
  "individual": [
    {
      "code": "01",
      "title": "HᵃKᵃ 上标融合",
      "description": "小尺寸读 HK，大尺寸补全 HaKa",
      "path": "D:\\projects\\practice\\haka_comic\\assets\\icons\\concepts\\haka-combo-01.png"
    },
    {
      "code": "02",
      "title": "Ha/Ka 上下锁定",
      "description": "最稳妥，四字母保持正方形",
      "path": "D:\\projects\\practice\\haka_comic\\assets\\icons\\concepts\\haka-combo-02.png"
    },
    {
      "code": "03",
      "title": "四宫格 HaKa",
      "description": "像一个紧凑字章，漫画感更强",
      "path": "D:\\projects\\practice\\haka_comic\\assets\\icons\\concepts\\haka-combo-03.png"
    },
    {
      "code": "04",
      "title": "共用主干 HK+a+a",
      "description": "最像图形 logo，但可读性更抽象",
      "path": "D:\\projects\\practice\\haka_comic\\assets\\icons\\concepts\\haka-combo-04.png"
    },
    {
      "code": "05",
      "title": "紧凑 HaKa 字标",
      "description": "最直接完整，但 16px 压力最大",
      "path": "D:\\projects\\practice\\haka_comic\\assets\\icons\\concepts\\haka-combo-05.png"
    },
    {
      "code": "06",
      "title": "主 Ha + 右下 Ka",
      "description": "保留现有识别，小尺寸仍偏 Ha",
      "path": "D:\\projects\\practice\\haka_comic\\assets\\icons\\concepts\\haka-combo-06.png"
    }
  ]
}